async_receiver/__init__.py
async_receiver/module/__init__.py
async_receiver/module/attributes.py
async_receiver/receiver/__init__.py
async_receiver/receiver/receive_manager.py
async_receiver/receiver/receiver.py
async_receiver/subprocess/__init__.py
async_receiver/subprocess/async_python_subprocess.py
async_receiver/subprocess/async_subprocess.py
async_receiver/subprocess/async_virtual_environment.py
async_receiver-0.0.3.dist-info/LICENSE
async_receiver-0.0.3.dist-info/METADATA
async_receiver-0.0.3.dist-info/WHEEL
async_receiver-0.0.3.dist-info/top_level.txt
async_receiver-0.0.3.dist-info/RECORD
